simple_stats/__init__.py
simple_stats/simple_stats.py
simple_stats-0.4.0.dist-info/AUTHORS.rst
simple_stats-0.4.0.dist-info/LICENSE
simple_stats-0.4.0.dist-info/METADATA
simple_stats-0.4.0.dist-info/WHEEL
simple_stats-0.4.0.dist-info/top_level.txt
simple_stats-0.4.0.dist-info/RECORD
