Metadata-Version: 2.1
Name: simple-stats
Version: 0.4.0
Summary: A Python package containing methods for EDA, bootstrapping, and hypothesis testing
Home-page: https://github.com/bfulroth/simple_stats
Author: Ben Fulroth
Author-email: fulrothb@icloud.com
License: MIT license
Keywords: simple_stats
Platform: UNKNOWN
Classifier: Development Status :: 2 - Pre-Alpha
Classifier: Intended Audience :: Developers
Classifier: License :: OSI Approved :: MIT License
Classifier: Natural Language :: English
Classifier: Programming Language :: Python :: 3
Classifier: Programming Language :: Python :: 3.5
Classifier: Programming Language :: Python :: 3.6
Classifier: Programming Language :: Python :: 3.7
Classifier: Programming Language :: Python :: 3.8
Requires-Python: >=3.5
Requires-Dist: numpy
